rws_nwb_lib/__init__.py
rws_nwb_lib/config.py
rws_nwb_lib/download_nwb.py
tests/__init__.py
tests/test_rws_nwb_lib.py
rws_nwb_lib-1.0.1.dist-info/LICENSE
rws_nwb_lib-1.0.1.dist-info/METADATA
rws_nwb_lib-1.0.1.dist-info/NOTICE
rws_nwb_lib-1.0.1.dist-info/WHEEL
rws_nwb_lib-1.0.1.dist-info/top_level.txt
rws_nwb_lib-1.0.1.dist-info/RECORD
