Metadata-Version: 2.1
Name: rws-nwb-lib
Version: 1.0.1
Summary: Library for automatically downloading the Dutch Nationaal Wegenbestand (NWB)
Home-page: https://gitlab.com/rwsdatalab/public/codebase/tools/rws-nwb-lib
Author: Datalab
Author-email: datalab.codebase@rws.nl
License: Apache Software License 2.0
Download-URL: https://gitlab.com/rwsdatalab/public/codebase/tools/rws-nwb-lib/-/archive/1.0.1.tar.gz
Platform: UNKNOWN
Classifier: Programming Language :: Python :: 3
Classifier: Operating System :: OS Independent
Requires-Python: >=3
License-File: LICENSE
Requires-Dist: geopandas
Requires-Dist: pydantic
Requires-Dist: requests
